flask_waf/__init__.py
flask_waf/anomaly_detection.py
flask_waf/config.py
flask_waf/content_security.py
flask_waf/geo_ip.py
flask_waf/logging.py
flask_waf/rate_limiter.py
flask_waf/rules.py
flask_waf/session_protection.py
flask_waf/threat_intelligence.py
flask_waf/waf.py
flask_waf-2.1.1.dist-info/licenses/LICENCE
flask_waf-2.1.1.dist-info/METADATA
flask_waf-2.1.1.dist-info/WHEEL
flask_waf-2.1.1.dist-info/top_level.txt
flask_waf-2.1.1.dist-info/RECORD
