Metadata-Version: 2.4
Name: flask_waf
Version: 2.1.1
Summary: Flask-WAF is an advanced Web Application Firewall (WAF) extension for Flask applications. It provides comprehensive protection against various web application threats, enhancing the security of your Flask-based web applications.
Home-page: https://github.com/ishanoshada/Flask-Waf
Author: Ishan Oshada
Author-email: ic31908@gmail.com
Classifier: Programming Language :: Python :: 3
Classifier: License :: OSI Approved :: MIT License
Classifier: Operating System :: OS Independent
License-File: LICENCE
Dynamic: author
Dynamic: author-email
Dynamic: classifier
Dynamic: description
Dynamic: description-content-type
Dynamic: home-page
Dynamic: license-file
Dynamic: summary
